{
    "_runs_": {
        "run_1457574598_bcfe8464-c37e-4588-96e6-65ba371be1a8": {
            "downloading": {
                "gnos-download_time": 118, 
                "start": 1457585917, 
                "stop": 1457586035, 
                "time": 118
            }, 
            "uploading": {
                "start": 1457586054, 
                "stop": 1457586111, 
                "time": 57, 
                "upload_time": 56
            }
        }, 
        "run_1458005660_73adae83-3fcb-4802-9c6a-c5787060c150": {
            "downloading": {
                "gnos-download_time": 126, 
                "start": 1458011131, 
                "stop": 1458011257, 
                "time": 126
            }
        }
    }, 
    "aliquot_id": null, 
    "available_repos": [
        {
            "https://gtrepo-osdc-icgc.annailabs.com/": {
                "file_md5sum": "9649c9e19f8afce1b3b587b453120b1b", 
                "file_size": 38819
            }
        }
    ], 
    "data_type": "Broad-VCF", 
    "files": [
        {
            "file_md5sum": "1f9f1a60f417dbd94effc809564931ee", 
            "file_name": "68054218-c623-11e3-bf01-24c6515278c0.broad-mutect-v3.20160222.somatic.snv_mnv.vcf.gz", 
            "file_size": 248291, 
            "object_id": "9fce11ca-5af3-5cc1-a76b-ef09cc87090a"
        }, 
        {
            "file_md5sum": "4e1eba4010b3bfb5462a3df57b041689", 
            "file_name": "68054218-c623-11e3-bf01-24c6515278c0.broad-mutect-v3.20160222.somatic.snv_mnv.vcf.gz.idx", 
            "file_size": 98755, 
            "object_id": "6df80321-b528-5a77-a99e-cc1e5220abf0"
        }, 
        {
            "file_md5sum": "f9810a896cafd8ef86577ab50b5108e3", 
            "file_name": "68054218-c623-11e3-bf01-24c6515278c0.broad-snowman-10.20151220.somatic.sv.vcf.gz", 
            "file_size": 192901, 
            "object_id": "acc7f6fb-9e4c-5973-9e69-39a72e4ad46e"
        }, 
        {
            "file_md5sum": "67ee6e2e9e253bff6176c5d15d3009e5", 
            "file_name": "68054218-c623-11e3-bf01-24c6515278c0.broad-snowman-10.20151220.germline.sv.vcf.gz", 
            "file_size": 2040490, 
            "object_id": "82970c23-b81e-56f5-b23c-d72e71c90d7a"
        }, 
        {
            "file_md5sum": "8e22b1d18d7e03ae8e2fd6a66aba9200", 
            "file_name": "68054218-c623-11e3-bf01-24c6515278c0.broad-dRanger_snowman-10.20151220.somatic.sv.vcf.gz", 
            "file_size": 197339, 
            "object_id": "43c48af8-2dd9-581d-9ea9-040779c89db5"
        }, 
        {
            "file_md5sum": "1bcf9494468845523d47db11d853bd5d", 
            "file_name": "68054218-c623-11e3-bf01-24c6515278c0.broad-dRanger_snowman-10.20151220.somatic.sv.vcf.gz.idx", 
            "file_size": 14336, 
            "object_id": "cccf54a7-7cbf-53a7-b735-45d1e60aecf3"
        }, 
        {
            "file_md5sum": "4065a5641b7c8f3e405a688c34c11da8", 
            "file_name": "68054218-c623-11e3-bf01-24c6515278c0.broad-dRanger-10.20151220.somatic.sv.vcf.gz", 
            "file_size": 120857, 
            "object_id": "7dd0a80b-22fe-5d8c-9e3e-b9899999d316"
        }, 
        {
            "file_md5sum": "96763d3545b11fa42cdfc6114bbbcd1e", 
            "file_name": "68054218-c623-11e3-bf01-24c6515278c0.broad-snowman-10.20151220.somatic.indel.vcf.gz.idx", 
            "file_size": 16617, 
            "object_id": "d2147f77-b0d1-541e-8f45-180c75a7637b"
        }, 
        {
            "file_md5sum": "99773cb3ef1f00653bae9af1dafffbb4", 
            "file_name": "68054218-c623-11e3-bf01-24c6515278c0.broad-dRanger-10.20151220.somatic.sv.vcf.gz.idx", 
            "file_size": 10646, 
            "object_id": "a9c799b6-c7c6-5e17-a031-33c087cf5792"
        }, 
        {
            "file_md5sum": "fac2483712289b417658d6c3f472b4b9", 
            "file_name": "68054218-c623-11e3-bf01-24c6515278c0.broad-snowman-10.20151220.germline.indel.vcf.gz", 
            "file_size": 11103300, 
            "object_id": "c97d0608-c477-5b2c-9bd0-d974fbd76c1c"
        }, 
        {
            "file_md5sum": "b57b32793687dc22c9ec996cbd32694a", 
            "file_name": "68054218-c623-11e3-bf01-24c6515278c0.broad-snowman-10.20151220.germline.indel.vcf.gz.idx", 
            "file_size": 1053362, 
            "object_id": "7db8af3b-bd1e-5d02-bd9e-84bc36d260b9"
        }, 
        {
            "file_md5sum": "852359385e2031ef0df137fa35bd6942", 
            "file_name": "68054218-c623-11e3-bf01-24c6515278c0.broad-snowman-10.20151220.somatic.sv.vcf.gz.idx", 
            "file_size": 14217, 
            "object_id": "47148ce3-5943-5aba-bf3e-2974139d3599"
        }, 
        {
            "file_md5sum": "5cb0b6f04078b1c90472c58ebb287092", 
            "file_name": "68054218-c623-11e3-bf01-24c6515278c0.broad-snowman-10.20151220.germline.sv.vcf.gz.idx", 
            "file_size": 66158, 
            "object_id": "039194b8-ddb0-5f48-944a-80264c5b677a"
        }, 
        {
            "file_md5sum": "4ff2cdde242cda5cd710cb96eb6bcfdb", 
            "file_name": "68054218-c623-11e3-bf01-24c6515278c0.broad-snowman-10.20151220.somatic.indel.vcf.gz", 
            "file_size": 39123, 
            "object_id": "e1e54504-a7c9-5f91-bc2d-f8097d2975b9"
        }, 
        {
            "file_md5sum": "9649c9e19f8afce1b3b587b453120b1b", 
            "file_name": "b3a22744-75ea-4a0a-b995-19fd6ff3a861.xml", 
            "file_size": 38819, 
            "object_id": "8fb5cea5-5e61-5d11-9b11-ad686c7a2eb5"
        }
    ], 
    "gnos_id": "b3a22744-75ea-4a0a-b995-19fd6ff3a861", 
    "gnos_repo": [
        "https://gtrepo-osdc-icgc.annailabs.com/"
    ], 
    "project_code": "LIRI-JP", 
    "specimen_type": null, 
    "submitter_donor_id": "RK285", 
    "submitter_sample_id": null, 
    "submitter_specimen_id": null, 
    "vcf_workflow_result_version": "v3"
}