{
    "_runs_": {
        "run_1473909420_cd8c23df-fed3-409e-8ccb-05b9d39c66fc": {
            "downloading": {
                "gnos-download_time": 19, 
                "start": 1473909793, 
                "stop": 1473909812, 
                "time": 19
            }, 
            "uploading": {
                "copy_meta_time": 1, 
                "start": 1473909824, 
                "stop": 1473909841, 
                "time": 17, 
                "upload_time": 16
            }
        }
    }, 
    "aliquot_id": "0972bfcf-c6c6-48cc-b820-cdfa6279a4f3", 
    "available_repos": [
        {
            "https://gtrepo-osdc-icgc.annailabs.com/": {
                "file_md5sum": "5881e41d68b74e5b8436be40e72f8fda", 
                "file_size": 31827
            }
        }
    ], 
    "data_type": "Consensus-somatic-SNV_MNV", 
    "files": [
        {
            "file_md5sum": "88834c108cc2d17f27cf405ca4ff6133", 
            "file_name": "0972bfcf-c6c6-48cc-b820-cdfa6279a4f3.consensus.20160830.somatic.snv_mnv.vcf.gz", 
            "file_size": 368001, 
            "object_id": "3a87b45c-3b45-5ce2-bf88-3bad40a6e28e"
        }, 
        {
            "file_md5sum": "c3e51bb0747226d331910911c67f8c01", 
            "file_name": "0972bfcf-c6c6-48cc-b820-cdfa6279a4f3.consensus.20160830.somatic.snv_mnv.vcf.gz.tbi", 
            "file_size": 174852, 
            "object_id": "94845d31-f245-5d70-aa7f-df1166990602"
        }, 
        {
            "file_md5sum": "5881e41d68b74e5b8436be40e72f8fda", 
            "file_name": "17b951ba-8881-4dd2-84b0-59251c03603a.xml", 
            "file_size": 31827, 
            "object_id": "ef696450-2d70-5a32-b89d-7ad95b9248bc"
        }
    ], 
    "gnos_id": "17b951ba-8881-4dd2-84b0-59251c03603a", 
    "gnos_repo": [
        "https://gtrepo-osdc-icgc.annailabs.com/"
    ], 
    "project_code": "PACA-CA", 
    "specimen_type": null, 
    "submitter_donor_id": "PCSI_0325", 
    "submitter_sample_id": null, 
    "submitter_specimen_id": "0972bfcf-c6c6-48cc-b820-cdfa6279a4f3", 
    "vcf_workflow_result_version": "v1"
}