{
    "_runs_": {
        "run_1454298561_7b11da6b-96aa-4dd1-b243-b9041326427c": {
            "downloading": {
                "gnos-download_time": 27, 
                "start": 1454310100, 
                "stop": 1454310127, 
                "time": 27
            }, 
            "uploading": {
                "copy_meta_time": 1, 
                "start": 1454310132, 
                "stop": 1454310147, 
                "time": 15, 
                "upload_time": 14
            }
        }, 
        "run_1454434668_8a5aa7f7-e742-4ab6-9715-7047d070f1ed": {
            "downloading": {
                "665392a3-0059-4002-a672-57d3a6308f02.xml-download_time": 12, 
                "665392a3-0059-4002-a672-57d3a6308f02.xml-md5sum_time": 0, 
                "82aefe8e-c622-11e3-bf01-24c6515278c0.MUSE_1-0rc-b391201-vcf.20151218.somatic.snv_mnv.vcf.gz-download_time": 13, 
                "82aefe8e-c622-11e3-bf01-24c6515278c0.MUSE_1-0rc-b391201-vcf.20151218.somatic.snv_mnv.vcf.gz-md5sum_time": 0, 
                "82aefe8e-c622-11e3-bf01-24c6515278c0.MUSE_1-0rc-b391201-vcf.20151218.somatic.snv_mnv.vcf.gz.idx-download_time": 14, 
                "82aefe8e-c622-11e3-bf01-24c6515278c0.MUSE_1-0rc-b391201-vcf.20151218.somatic.snv_mnv.vcf.gz.idx-md5sum_time": 0, 
                "start": 1454446067, 
                "stop": 1454446106, 
                "time": 39
            }
        }
    }, 
    "aliquot_id": null, 
    "available_repos": [
        {
            "https://gtrepo-osdc-icgc.annailabs.com/": {
                "file_md5sum": "9521f3458460f202cee57d58c18e7563", 
                "file_size": 34688
            }
        }
    ], 
    "data_type": "Muse-VCF", 
    "files": [
        {
            "file_md5sum": "11421c380310f00a15dd70de14c374a1", 
            "file_name": "82aefe8e-c622-11e3-bf01-24c6515278c0.MUSE_1-0rc-b391201-vcf.20151218.somatic.snv_mnv.vcf.gz", 
            "file_size": 317052, 
            "object_id": "45ff5967-296e-51a6-b1fc-49c8cf4e2201"
        }, 
        {
            "file_md5sum": "bdb817e92e12882a8d65d0e2095d0938", 
            "file_name": "82aefe8e-c622-11e3-bf01-24c6515278c0.MUSE_1-0rc-b391201-vcf.20151218.somatic.snv_mnv.vcf.gz.idx", 
            "file_size": 165589, 
            "object_id": "7c6a3370-775d-54c3-be65-fed4a678cdf2"
        }, 
        {
            "file_md5sum": "9521f3458460f202cee57d58c18e7563", 
            "file_name": "665392a3-0059-4002-a672-57d3a6308f02.xml", 
            "file_size": 34688, 
            "object_id": "ce4e5364-f18c-53b2-b2b4-f64642889c7c"
        }
    ], 
    "gnos_id": "665392a3-0059-4002-a672-57d3a6308f02", 
    "gnos_repo": [
        "https://gtrepo-osdc-icgc.annailabs.com/"
    ], 
    "project_code": "LIRI-JP", 
    "specimen_type": null, 
    "submitter_donor_id": "RK057", 
    "submitter_sample_id": null, 
    "submitter_specimen_id": null, 
    "vcf_workflow_result_version": "v1"
}