{
    "_runs_": {
        "run_1454298278_75dd4641-42c1-45d2-a4cb-1480434a27d0": {
            "downloading": {
                "gnos-download_time": 46, 
                "start": 1454324277, 
                "stop": 1454324324, 
                "time": 47
            }, 
            "uploading": {
                "copy_meta_time": 1, 
                "start": 1454324336, 
                "stop": 1454324352, 
                "time": 16, 
                "upload_time": 15
            }
        }, 
        "run_1454434600_3a13e3c4-1d69-436a-bb85-219a15f3e4aa": {
            "downloading": {
                "9650640f-154d-4696-aa96-3611c6fcee7b.MUSE_1-0rc-vcf.20151215.somatic.snv_mnv.vcf.gz-download_time": 13, 
                "9650640f-154d-4696-aa96-3611c6fcee7b.MUSE_1-0rc-vcf.20151215.somatic.snv_mnv.vcf.gz-md5sum_time": 0, 
                "9650640f-154d-4696-aa96-3611c6fcee7b.MUSE_1-0rc-vcf.20151215.somatic.snv_mnv.vcf.gz.idx-download_time": 13, 
                "9650640f-154d-4696-aa96-3611c6fcee7b.MUSE_1-0rc-vcf.20151215.somatic.snv_mnv.vcf.gz.idx-md5sum_time": 0, 
                "dd9e04c2-f91f-40bf-8417-660ef6d567fb.xml-download_time": 12, 
                "dd9e04c2-f91f-40bf-8417-660ef6d567fb.xml-md5sum_time": 0, 
                "start": 1454460307, 
                "stop": 1454460345, 
                "time": 38
            }
        }
    }, 
    "aliquot_id": null, 
    "available_repos": [
        {
            "https://gtrepo-osdc-icgc.annailabs.com/": {
                "file_md5sum": "97fa8d5b0a892009fbb46a836baf3d46", 
                "file_size": 35644
            }
        }
    ], 
    "data_type": "Muse-VCF", 
    "files": [
        {
            "file_md5sum": "5be3be3536be10abd480bb21fae56b2c", 
            "file_name": "9650640f-154d-4696-aa96-3611c6fcee7b.MUSE_1-0rc-vcf.20151215.somatic.snv_mnv.vcf.gz", 
            "file_size": 323775, 
            "object_id": "3696759f-e06c-51b0-b8a8-0f023c8531f0"
        }, 
        {
            "file_md5sum": "ba25e72287233dd53fb9352703679f3f", 
            "file_name": "9650640f-154d-4696-aa96-3611c6fcee7b.MUSE_1-0rc-vcf.20151215.somatic.snv_mnv.vcf.gz.idx", 
            "file_size": 165792, 
            "object_id": "7998cabc-22d3-5ced-b35b-77732aa81fdf"
        }, 
        {
            "file_md5sum": "97fa8d5b0a892009fbb46a836baf3d46", 
            "file_name": "dd9e04c2-f91f-40bf-8417-660ef6d567fb.xml", 
            "file_size": 35644, 
            "object_id": "60c4812d-0e43-5221-9111-d606de9e61af"
        }
    ], 
    "gnos_id": "dd9e04c2-f91f-40bf-8417-660ef6d567fb", 
    "gnos_repo": [
        "https://gtrepo-osdc-icgc.annailabs.com/"
    ], 
    "project_code": "ORCA-IN", 
    "specimen_type": null, 
    "submitter_donor_id": "OSCC-GB_012501", 
    "submitter_sample_id": null, 
    "submitter_specimen_id": null, 
    "vcf_workflow_result_version": "v1"
}