{
    "aliquot_id": "2c48eefe-2a08-47bf-8e4d-cbaab6777150", 
    "available_repos": [
        {
            "https://gtrepo-osdc-icgc.annailabs.com/": {
                "file_md5sum": "29154bad91b84ea8250df0d78796afb9", 
                "file_size": 33285
            }
        }
    ], 
    "data_type": "Consensus-somatic-INDEL", 
    "files": [
        {
            "file_md5sum": "ec7c1bd64f1f650471f5ad9fb205d978", 
            "file_name": "2c48eefe-2a08-47bf-8e4d-cbaab6777150.consensus.20161006.somatic.indel.vcf.gz", 
            "file_size": 45788, 
            "object_id": "31be3247-9d7d-5c11-b09f-970460c7e8fa"
        }, 
        {
            "file_md5sum": "89ab60a78b8c9899e64ddc743e22ba58", 
            "file_name": "2c48eefe-2a08-47bf-8e4d-cbaab6777150.consensus.20161006.somatic.indel.vcf.gz.tbi", 
            "file_size": 21200, 
            "object_id": "58819103-6159-5d4b-8f3e-cd2e7df01091"
        }, 
        {
            "file_md5sum": "29154bad91b84ea8250df0d78796afb9", 
            "file_name": "30bca41c-092a-4930-9125-529979b72c1c.xml", 
            "file_size": 33285, 
            "object_id": "9c01ee4a-4bbc-595c-bdff-d582da06329e"
        }
    ], 
    "gnos_id": "30bca41c-092a-4930-9125-529979b72c1c", 
    "gnos_repo": [
        "https://gtrepo-osdc-icgc.annailabs.com/"
    ], 
    "project_code": "PACA-CA", 
    "specimen_type": null, 
    "submitter_donor_id": "PCSI_0081", 
    "submitter_sample_id": null, 
    "submitter_specimen_id": "2c48eefe-2a08-47bf-8e4d-cbaab6777150", 
    "vcf_workflow_result_version": "v1"
}