{
    "aliquot_id": "f856fa85-fdb8-c0b0-e040-11ac0d480b4e", 
    "available_repos": [
        {
            "https://gtrepo-osdc-icgc.annailabs.com/": {
                "file_md5sum": "274aa0e54ca8632903ca45903a8e2a5e", 
                "file_size": 31539
            }
        }
    ], 
    "data_type": "Consensus-somatic-INDEL", 
    "files": [
        {
            "file_md5sum": "5acd331ceab49d6c78c571221e44ed32", 
            "file_name": "f856fa85-fdb8-c0b0-e040-11ac0d480b4e.consensus.20160830.somatic.indel.vcf.gz", 
            "file_size": 20498, 
            "object_id": "b040ac1f-3656-531b-9955-59513e17e7c6"
        }, 
        {
            "file_md5sum": "2e7e25d70abae469d636039d77cf6ff4", 
            "file_name": "f856fa85-fdb8-c0b0-e040-11ac0d480b4e.consensus.20160830.somatic.indel.vcf.gz.tbi", 
            "file_size": 11404, 
            "object_id": "413e6112-1cfc-5640-abaf-a73268d08903"
        }, 
        {
            "file_md5sum": "274aa0e54ca8632903ca45903a8e2a5e", 
            "file_name": "c1c5ec0b-241d-45a0-b66c-8d8486cb415d.xml", 
            "file_size": 31539, 
            "object_id": "3b155a30-962f-5da6-ad34-0b43ee260c4e"
        }
    ], 
    "gnos_id": "c1c5ec0b-241d-45a0-b66c-8d8486cb415d", 
    "gnos_repo": [
        "https://gtrepo-osdc-icgc.annailabs.com/"
    ], 
    "project_code": "BOCA-UK", 
    "specimen_type": null, 
    "submitter_donor_id": "CGP_donor_1397080", 
    "submitter_sample_id": null, 
    "submitter_specimen_id": "f856fa85-fdb8-c0b0-e040-11ac0d480b4e", 
    "vcf_workflow_result_version": "v1"
}