{
    "aliquot_id": "edac1323-2497-45e6-9148-e9c955292ba2", 
    "available_repos": [
        {
            "https://gtrepo-osdc-icgc.annailabs.com/": {
                "file_md5sum": "671c2022662e924dff2359d21db571e6", 
                "file_size": 31821
            }
        }
    ], 
    "data_type": "Consensus-somatic-INDEL", 
    "files": [
        {
            "file_md5sum": "e9dd48addeba68e62dbc754659c57e18", 
            "file_name": "edac1323-2497-45e6-9148-e9c955292ba2.consensus.20160830.somatic.indel.vcf.gz", 
            "file_size": 45768, 
            "object_id": "11692755-11d6-5a96-87ca-a1c854e7bff4"
        }, 
        {
            "file_md5sum": "d06d2927a753220301b97ca801714733", 
            "file_name": "edac1323-2497-45e6-9148-e9c955292ba2.consensus.20160830.somatic.indel.vcf.gz.tbi", 
            "file_size": 21130, 
            "object_id": "9af868cb-ab97-5067-982d-a8553eebfec2"
        }, 
        {
            "file_md5sum": "671c2022662e924dff2359d21db571e6", 
            "file_name": "2bc5ad24-2f92-473e-a716-6b3b4e993514.xml", 
            "file_size": 31821, 
            "object_id": "9cac0b9c-553d-59fc-b6f2-99075bde3f96"
        }
    ], 
    "gnos_id": "2bc5ad24-2f92-473e-a716-6b3b4e993514", 
    "gnos_repo": [
        "https://gtrepo-osdc-icgc.annailabs.com/"
    ], 
    "project_code": "PACA-AU", 
    "specimen_type": null, 
    "submitter_donor_id": "ICGC_0115", 
    "submitter_sample_id": null, 
    "submitter_specimen_id": "edac1323-2497-45e6-9148-e9c955292ba2", 
    "vcf_workflow_result_version": "v1"
}