{
    "aliquot_id": "ed7be9ae-e603-4731-8d91-a8285abaee33", 
    "available_repos": [
        {
            "https://gtrepo-osdc-icgc.annailabs.com/": {
                "file_md5sum": "df5b2a88b738b936d3f4728ecefa9de9", 
                "file_size": 32152
            }
        }
    ], 
    "data_type": "Consensus-somatic-INDEL", 
    "files": [
        {
            "file_md5sum": "3b9e79c0d06ab6fc5f2273a642d151a1", 
            "file_name": "ed7be9ae-e603-4731-8d91-a8285abaee33.consensus.20160830.somatic.indel.vcf.gz", 
            "file_size": 162511, 
            "object_id": "7eba56dc-0a42-532f-b4b7-4fa1efe06d80"
        }, 
        {
            "file_md5sum": "301362ae5a567c07266421f5584c25cf", 
            "file_name": "ed7be9ae-e603-4731-8d91-a8285abaee33.consensus.20160830.somatic.indel.vcf.gz.tbi", 
            "file_size": 66305, 
            "object_id": "4af32a64-1ce3-5594-bf8f-fc5ae81b6a8b"
        }, 
        {
            "file_md5sum": "df5b2a88b738b936d3f4728ecefa9de9", 
            "file_name": "a1497787-33d9-4112-85df-86c3cd6d0db4.xml", 
            "file_size": 32152, 
            "object_id": "720f0c71-b196-53cf-b457-819d3105ecb7"
        }
    ], 
    "gnos_id": "a1497787-33d9-4112-85df-86c3cd6d0db4", 
    "gnos_repo": [
        "https://gtrepo-osdc-icgc.annailabs.com/"
    ], 
    "project_code": "PRAD-CA", 
    "specimen_type": null, 
    "submitter_donor_id": "CPCG0259", 
    "submitter_sample_id": null, 
    "submitter_specimen_id": "ed7be9ae-e603-4731-8d91-a8285abaee33", 
    "vcf_workflow_result_version": "v1"
}