{
    "aliquot_id": "d707940e-0f9d-4da3-9380-90a422e44efd", 
    "available_repos": [
        {
            "https://gtrepo-osdc-icgc.annailabs.com/": {
                "file_md5sum": "bfdafefd267aeafee5711dda760694dc", 
                "file_size": 32381
            }
        }
    ], 
    "data_type": "Consensus-somatic-INDEL", 
    "files": [
        {
            "file_md5sum": "a720dbbab731f970cd30cf873987d789", 
            "file_name": "d707940e-0f9d-4da3-9380-90a422e44efd.consensus.20160830.somatic.indel.vcf.gz", 
            "file_size": 117003, 
            "object_id": "a354c2be-f583-54ae-b2e9-d5c088a201c2"
        }, 
        {
            "file_md5sum": "ee6eb56b2c5b4151eb2b9615e8ce9a07", 
            "file_name": "d707940e-0f9d-4da3-9380-90a422e44efd.consensus.20160830.somatic.indel.vcf.gz.tbi", 
            "file_size": 49661, 
            "object_id": "e7baad1c-187a-5edb-a227-4f569436a930"
        }, 
        {
            "file_md5sum": "bfdafefd267aeafee5711dda760694dc", 
            "file_name": "ada0028a-2925-424b-aac2-f5123bd9c041.xml", 
            "file_size": 32381, 
            "object_id": "f95cd520-f425-5892-b44f-565ed28f1398"
        }
    ], 
    "gnos_id": "ada0028a-2925-424b-aac2-f5123bd9c041", 
    "gnos_repo": [
        "https://gtrepo-osdc-icgc.annailabs.com/"
    ], 
    "project_code": "ESAD-UK", 
    "specimen_type": null, 
    "submitter_donor_id": "OCCAMS-AH-120", 
    "submitter_sample_id": null, 
    "submitter_specimen_id": "d707940e-0f9d-4da3-9380-90a422e44efd", 
    "vcf_workflow_result_version": "v1"
}