{
    "aliquot_id": "48624a82-c623-11e3-bf01-24c6515278c0", 
    "available_repos": [
        {
            "https://gtrepo-osdc-icgc.annailabs.com/": {
                "file_md5sum": "368924ed78501a87999c38269f4d4dbf", 
                "file_size": 31321
            }
        }
    ], 
    "data_type": "Consensus-somatic-INDEL", 
    "files": [
        {
            "file_md5sum": "08ca5693243b5727dad828abe639e8d8", 
            "file_name": "48624a82-c623-11e3-bf01-24c6515278c0.consensus.20160830.somatic.indel.vcf.gz", 
            "file_size": 34422, 
            "object_id": "ff262d49-8b84-5c4c-9c09-79cb21bb41f3"
        }, 
        {
            "file_md5sum": "d7b7548efc5eb959498b5202d84ecb7b", 
            "file_name": "48624a82-c623-11e3-bf01-24c6515278c0.consensus.20160830.somatic.indel.vcf.gz.tbi", 
            "file_size": 18035, 
            "object_id": "e588ab90-c161-560a-abe7-9d2f42133d2b"
        }, 
        {
            "file_md5sum": "368924ed78501a87999c38269f4d4dbf", 
            "file_name": "e0ef5e64-99e3-4fc5-a805-7df9c52ad8d6.xml", 
            "file_size": 31321, 
            "object_id": "b9c278b7-82bf-5ee1-81f5-ae6613c9c4a7"
        }
    ], 
    "gnos_id": "e0ef5e64-99e3-4fc5-a805-7df9c52ad8d6", 
    "gnos_repo": [
        "https://gtrepo-osdc-icgc.annailabs.com/"
    ], 
    "project_code": "LIRI-JP", 
    "specimen_type": null, 
    "submitter_donor_id": "RK243", 
    "submitter_sample_id": null, 
    "submitter_specimen_id": "48624a82-c623-11e3-bf01-24c6515278c0", 
    "vcf_workflow_result_version": "v1"
}