{
    "aliquot_id": "33bcd589-80db-4a58-8f83-a48cb60e0fda", 
    "available_repos": [
        {
            "https://gtrepo-osdc-icgc.annailabs.com/": {
                "file_md5sum": "2e79193d64ff830fbfbe3b8d5a186f12", 
                "file_size": 38649
            }
        }
    ], 
    "data_type": "Consensus-somatic-SNV_MNV", 
    "files": [
        {
            "file_md5sum": "60e3883cd961b5ccc644aad5dcdf2e52", 
            "file_name": "33bcd589-80db-4a58-8f83-a48cb60e0fda.consensus.20160830.somatic.snv_mnv.vcf.gz", 
            "file_size": 123019, 
            "object_id": "33105721-4b6f-50a4-b8a0-b355a664dd0f"
        }, 
        {
            "file_md5sum": "3016660461a6a1f0414c35f7b3be9845", 
            "file_name": "33bcd589-80db-4a58-8f83-a48cb60e0fda.consensus.20160830.somatic.snv_mnv.vcf.gz.tbi", 
            "file_size": 58537, 
            "object_id": "e5b07be9-de46-5d2b-b069-8e1e9db947e9"
        }, 
        {
            "file_md5sum": "2e79193d64ff830fbfbe3b8d5a186f12", 
            "file_name": "a7d3f568-4cab-4a41-bfb0-6fb2721eb993.xml", 
            "file_size": 38649, 
            "object_id": "6e7f8e68-86fb-54fb-966c-875087bbe06c"
        }
    ], 
    "gnos_id": "a7d3f568-4cab-4a41-bfb0-6fb2721eb993", 
    "gnos_repo": [
        "https://gtrepo-osdc-icgc.annailabs.com/"
    ], 
    "project_code": "PACA-CA", 
    "specimen_type": null, 
    "submitter_donor_id": "PCSI_0106", 
    "submitter_sample_id": null, 
    "submitter_specimen_id": "33bcd589-80db-4a58-8f83-a48cb60e0fda", 
    "vcf_workflow_result_version": "v1"
}