{
    "aliquot_id": "0b29c893-03bf-4131-b192-c14a2788d411", 
    "available_repos": [
        {
            "https://gtrepo-osdc-icgc.annailabs.com/": {
                "file_md5sum": "d99030b5659268edff0b4477d8feb622", 
                "file_size": 32257
            }
        }
    ], 
    "data_type": "Consensus-somatic-SNV_MNV", 
    "files": [
        {
            "file_md5sum": "1c0137a9fb890fefa0dc3b07b0d150bd", 
            "file_name": "0b29c893-03bf-4131-b192-c14a2788d411.consensus.20160830.somatic.snv_mnv.vcf.gz", 
            "file_size": 515631, 
            "object_id": "5b326b28-cccb-5bed-bafa-8ec37150349b"
        }, 
        {
            "file_md5sum": "ea41449f9829a005110f0065d46b2b9f", 
            "file_name": "0b29c893-03bf-4131-b192-c14a2788d411.consensus.20160830.somatic.snv_mnv.vcf.gz.tbi", 
            "file_size": 211268, 
            "object_id": "ee4fb7db-d220-5bf7-b4ff-0334883c0eb1"
        }, 
        {
            "file_md5sum": "d99030b5659268edff0b4477d8feb622", 
            "file_name": "f12234d1-00dc-473a-9e6b-1fff1397e041.xml", 
            "file_size": 32257, 
            "object_id": "e0fe374f-a461-5056-b5ba-4bdd461303c9"
        }
    ], 
    "gnos_id": "f12234d1-00dc-473a-9e6b-1fff1397e041", 
    "gnos_repo": [
        "https://gtrepo-osdc-icgc.annailabs.com/"
    ], 
    "project_code": "PACA-CA", 
    "specimen_type": null, 
    "submitter_donor_id": "PCSI_0164", 
    "submitter_sample_id": null, 
    "submitter_specimen_id": "0b29c893-03bf-4131-b192-c14a2788d411", 
    "vcf_workflow_result_version": "v1"
}