{
    "_runs_": {
        "run_1449082788_da7d6552-5b48-4b75-8085-235c65df5206": {
            "downloading": {
                "gnos-download_time": 838, 
                "start": 1449109244, 
                "stop": 1449110083, 
                "time": 839
            }, 
            "uploading": {
                "copy_meta_time": 1, 
                "start": 1449110100, 
                "stop": 1449110359, 
                "time": 259, 
                "upload_time": 257
            }
        }, 
        "run_1449256082_1952fd1a-a01c-401b-a592-79b18b22a57e": {
            "downloading": {
                "19a38b6b-24b2-4148-83f7-c177e59937fc.xml-download_time": 13, 
                "19a38b6b-24b2-4148-83f7-c177e59937fc.xml-md5sum_time": 0, 
                "94244f28-4ba2-4aa6-a0fb-0cd9b94bf9cc.dkfz-copyNumberEstimation_1-0-189-hpc.1510221004.somatic.cnv.tar.gz-download_time": 272, 
                "94244f28-4ba2-4aa6-a0fb-0cd9b94bf9cc.dkfz-copyNumberEstimation_1-0-189-hpc.1510221004.somatic.cnv.tar.gz-md5sum_time": 25, 
                "94244f28-4ba2-4aa6-a0fb-0cd9b94bf9cc.dkfz-copyNumberEstimation_1-0-189-hpc.1510221004.somatic.cnv.vcf.gz-download_time": 13, 
                "94244f28-4ba2-4aa6-a0fb-0cd9b94bf9cc.dkfz-copyNumberEstimation_1-0-189-hpc.1510221004.somatic.cnv.vcf.gz-md5sum_time": 0, 
                "94244f28-4ba2-4aa6-a0fb-0cd9b94bf9cc.dkfz-copyNumberEstimation_1-0-189-hpc.1510221004.somatic.cnv.vcf.gz.tbi-download_time": 13, 
                "94244f28-4ba2-4aa6-a0fb-0cd9b94bf9cc.dkfz-copyNumberEstimation_1-0-189-hpc.1510221004.somatic.cnv.vcf.gz.tbi-md5sum_time": 0, 
                "94244f28-4ba2-4aa6-a0fb-0cd9b94bf9cc.dkfz-indelCalling_1-0-132-1-hpc.1510221004.germline.indel.vcf.gz-download_time": 18, 
                "94244f28-4ba2-4aa6-a0fb-0cd9b94bf9cc.dkfz-indelCalling_1-0-132-1-hpc.1510221004.germline.indel.vcf.gz-md5sum_time": 0, 
                "94244f28-4ba2-4aa6-a0fb-0cd9b94bf9cc.dkfz-indelCalling_1-0-132-1-hpc.1510221004.germline.indel.vcf.gz.tbi-download_time": 15, 
                "94244f28-4ba2-4aa6-a0fb-0cd9b94bf9cc.dkfz-indelCalling_1-0-132-1-hpc.1510221004.germline.indel.vcf.gz.tbi-md5sum_time": 0, 
                "94244f28-4ba2-4aa6-a0fb-0cd9b94bf9cc.dkfz-indelCalling_1-0-132-1-hpc.1510221004.somatic.indel.tar.gz-download_time": 51, 
                "94244f28-4ba2-4aa6-a0fb-0cd9b94bf9cc.dkfz-indelCalling_1-0-132-1-hpc.1510221004.somatic.indel.tar.gz-md5sum_time": 3, 
                "94244f28-4ba2-4aa6-a0fb-0cd9b94bf9cc.dkfz-indelCalling_1-0-132-1-hpc.1510221004.somatic.indel.vcf.gz-download_time": 14, 
                "94244f28-4ba2-4aa6-a0fb-0cd9b94bf9cc.dkfz-indelCalling_1-0-132-1-hpc.1510221004.somatic.indel.vcf.gz-md5sum_time": 0, 
                "94244f28-4ba2-4aa6-a0fb-0cd9b94bf9cc.dkfz-indelCalling_1-0-132-1-hpc.1510221004.somatic.indel.vcf.gz.tbi-download_time": 14, 
                "94244f28-4ba2-4aa6-a0fb-0cd9b94bf9cc.dkfz-indelCalling_1-0-132-1-hpc.1510221004.somatic.indel.vcf.gz.tbi-md5sum_time": 0, 
                "94244f28-4ba2-4aa6-a0fb-0cd9b94bf9cc.dkfz-snvCalling_1-0-132-1-hpc.1510221004.germline.snv_mnv.vcf.gz-download_time": 21, 
                "94244f28-4ba2-4aa6-a0fb-0cd9b94bf9cc.dkfz-snvCalling_1-0-132-1-hpc.1510221004.germline.snv_mnv.vcf.gz-md5sum_time": 0, 
                "94244f28-4ba2-4aa6-a0fb-0cd9b94bf9cc.dkfz-snvCalling_1-0-132-1-hpc.1510221004.germline.snv_mnv.vcf.gz.tbi-download_time": 14, 
                "94244f28-4ba2-4aa6-a0fb-0cd9b94bf9cc.dkfz-snvCalling_1-0-132-1-hpc.1510221004.germline.snv_mnv.vcf.gz.tbi-md5sum_time": 0, 
                "94244f28-4ba2-4aa6-a0fb-0cd9b94bf9cc.dkfz-snvCalling_1-0-132-1-hpc.1510221004.somatic.snv_mnv.tar.gz-download_time": 98, 
                "94244f28-4ba2-4aa6-a0fb-0cd9b94bf9cc.dkfz-snvCalling_1-0-132-1-hpc.1510221004.somatic.snv_mnv.tar.gz-md5sum_time": 4, 
                "94244f28-4ba2-4aa6-a0fb-0cd9b94bf9cc.dkfz-snvCalling_1-0-132-1-hpc.1510221004.somatic.snv_mnv.vcf.gz-download_time": 14, 
                "94244f28-4ba2-4aa6-a0fb-0cd9b94bf9cc.dkfz-snvCalling_1-0-132-1-hpc.1510221004.somatic.snv_mnv.vcf.gz-md5sum_time": 0, 
                "94244f28-4ba2-4aa6-a0fb-0cd9b94bf9cc.dkfz-snvCalling_1-0-132-1-hpc.1510221004.somatic.snv_mnv.vcf.gz.tbi-download_time": 15, 
                "94244f28-4ba2-4aa6-a0fb-0cd9b94bf9cc.dkfz-snvCalling_1-0-132-1-hpc.1510221004.somatic.snv_mnv.vcf.gz.tbi-md5sum_time": 0, 
                "94244f28-4ba2-4aa6-a0fb-0cd9b94bf9cc.embl-delly_1-0-0-preFilter-hpc.150702.germline.sv.bedpe.txt.tar.gz-download_time": 14, 
                "94244f28-4ba2-4aa6-a0fb-0cd9b94bf9cc.embl-delly_1-0-0-preFilter-hpc.150702.germline.sv.bedpe.txt.tar.gz-md5sum_time": 0, 
                "94244f28-4ba2-4aa6-a0fb-0cd9b94bf9cc.embl-delly_1-0-0-preFilter-hpc.150702.germline.sv.readname.txt.tar.gz-download_time": 15, 
                "94244f28-4ba2-4aa6-a0fb-0cd9b94bf9cc.embl-delly_1-0-0-preFilter-hpc.150702.germline.sv.readname.txt.tar.gz-md5sum_time": 1, 
                "94244f28-4ba2-4aa6-a0fb-0cd9b94bf9cc.embl-delly_1-0-0-preFilter-hpc.150702.germline.sv.vcf.gz-download_time": 13, 
                "94244f28-4ba2-4aa6-a0fb-0cd9b94bf9cc.embl-delly_1-0-0-preFilter-hpc.150702.germline.sv.vcf.gz-md5sum_time": 0, 
                "94244f28-4ba2-4aa6-a0fb-0cd9b94bf9cc.embl-delly_1-0-0-preFilter-hpc.150702.germline.sv.vcf.gz.tbi-download_time": 13, 
                "94244f28-4ba2-4aa6-a0fb-0cd9b94bf9cc.embl-delly_1-0-0-preFilter-hpc.150702.germline.sv.vcf.gz.tbi-md5sum_time": 0, 
                "94244f28-4ba2-4aa6-a0fb-0cd9b94bf9cc.embl-delly_1-0-0-preFilter-hpc.150702.somatic.sv.bedpe.txt.tar.gz-download_time": 13, 
                "94244f28-4ba2-4aa6-a0fb-0cd9b94bf9cc.embl-delly_1-0-0-preFilter-hpc.150702.somatic.sv.bedpe.txt.tar.gz-md5sum_time": 0, 
                "94244f28-4ba2-4aa6-a0fb-0cd9b94bf9cc.embl-delly_1-0-0-preFilter-hpc.150702.somatic.sv.readname.txt.tar.gz-download_time": 14, 
                "94244f28-4ba2-4aa6-a0fb-0cd9b94bf9cc.embl-delly_1-0-0-preFilter-hpc.150702.somatic.sv.readname.txt.tar.gz-md5sum_time": 0, 
                "94244f28-4ba2-4aa6-a0fb-0cd9b94bf9cc.embl-delly_1-0-0-preFilter-hpc.150702.somatic.sv.vcf.gz-download_time": 13, 
                "94244f28-4ba2-4aa6-a0fb-0cd9b94bf9cc.embl-delly_1-0-0-preFilter-hpc.150702.somatic.sv.vcf.gz-md5sum_time": 0, 
                "94244f28-4ba2-4aa6-a0fb-0cd9b94bf9cc.embl-delly_1-0-0-preFilter-hpc.150702.somatic.sv.vcf.gz.tbi-download_time": 13, 
                "94244f28-4ba2-4aa6-a0fb-0cd9b94bf9cc.embl-delly_1-0-0-preFilter-hpc.150702.somatic.sv.vcf.gz.tbi-md5sum_time": 0, 
                "94244f28-4ba2-4aa6-a0fb-0cd9b94bf9cc.embl-delly_1-0-0-preFilter-hpc.150702.sv.log.tar.gz-download_time": 14, 
                "94244f28-4ba2-4aa6-a0fb-0cd9b94bf9cc.embl-delly_1-0-0-preFilter-hpc.150702.sv.log.tar.gz-md5sum_time": 0, 
                "94244f28-4ba2-4aa6-a0fb-0cd9b94bf9cc.embl-delly_1-0-0-preFilter-hpc.150702.sv.vcf.gz-download_time": 17, 
                "94244f28-4ba2-4aa6-a0fb-0cd9b94bf9cc.embl-delly_1-0-0-preFilter-hpc.150702.sv.vcf.gz-md5sum_time": 0, 
                "94244f28-4ba2-4aa6-a0fb-0cd9b94bf9cc.embl-delly_1-0-0-preFilter-hpc.150702.sv.vcf.gz.tbi-download_time": 14, 
                "94244f28-4ba2-4aa6-a0fb-0cd9b94bf9cc.embl-delly_1-0-0-preFilter-hpc.150702.sv.vcf.gz.tbi-md5sum_time": 0, 
                "start": 1449272750, 
                "stop": 1449273522, 
                "time": 772
            }
        }
    }, 
    "aliquot_id": null, 
    "available_repos": [
        {
            "https://gtrepo-dkfz.annailabs.com/": {
                "file_md5sum": "333514398b581ba263abecd7321eaab7", 
                "file_size": 51365
            }
        }
    ], 
    "data_type": "Dkfz_embl-VCF", 
    "files": [
        {
            "file_md5sum": "a8adbc39bc1457c166a145b1cb42aa15", 
            "file_name": "94244f28-4ba2-4aa6-a0fb-0cd9b94bf9cc.dkfz-copyNumberEstimation_1-0-189-hpc.1510221004.somatic.cnv.vcf.gz", 
            "file_size": 18961, 
            "object_id": "83806ac2-619e-5872-b1f4-29956871fd9f"
        }, 
        {
            "file_md5sum": "ba523fd0f2d9a2ab3e4c5881f412bb6b", 
            "file_name": "94244f28-4ba2-4aa6-a0fb-0cd9b94bf9cc.dkfz-copyNumberEstimation_1-0-189-hpc.1510221004.somatic.cnv.vcf.gz.tbi", 
            "file_size": 9484, 
            "object_id": "d1df12e7-e195-5b6c-b7eb-5088eb996356"
        }, 
        {
            "file_md5sum": "6f974c8c52ef3186fbc16cbc2b980f9e", 
            "file_name": "94244f28-4ba2-4aa6-a0fb-0cd9b94bf9cc.dkfz-indelCalling_1-0-132-1-hpc.1510221004.germline.indel.vcf.gz", 
            "file_size": 67320863, 
            "object_id": "e5e42919-2501-5521-b9a6-084459500eb8"
        }, 
        {
            "file_md5sum": "b862395110509efe496198ba6c0e7fdd", 
            "file_name": "94244f28-4ba2-4aa6-a0fb-0cd9b94bf9cc.dkfz-indelCalling_1-0-132-1-hpc.1510221004.germline.indel.vcf.gz.tbi", 
            "file_size": 1445050, 
            "object_id": "e3bdabda-f813-55a6-9b86-271dd1aabe05"
        }, 
        {
            "file_md5sum": "343cc7b8664503d73cab9698014b5e6b", 
            "file_name": "94244f28-4ba2-4aa6-a0fb-0cd9b94bf9cc.dkfz-indelCalling_1-0-132-1-hpc.1510221004.somatic.indel.vcf.gz", 
            "file_size": 1771629, 
            "object_id": "d419c4b2-aefb-54d4-a114-9334d16380e3"
        }, 
        {
            "file_md5sum": "369dc5f8e6adb3f4952e5fdd9a2bd57c", 
            "file_name": "94244f28-4ba2-4aa6-a0fb-0cd9b94bf9cc.dkfz-indelCalling_1-0-132-1-hpc.1510221004.somatic.indel.vcf.gz.tbi", 
            "file_size": 204591, 
            "object_id": "ad7c7797-7866-5ff4-b634-5098bd1208b7"
        }, 
        {
            "file_md5sum": "b39cde9224f77f3a90f2447f8fc9edaa", 
            "file_name": "94244f28-4ba2-4aa6-a0fb-0cd9b94bf9cc.dkfz-snvCalling_1-0-132-1-hpc.1510221004.germline.snv_mnv.vcf.gz", 
            "file_size": 105922790, 
            "object_id": "4e447a50-e4c8-5d17-8056-8c6b5fda9fde"
        }, 
        {
            "file_md5sum": "4630815d91103c8921c182af882e387d", 
            "file_name": "94244f28-4ba2-4aa6-a0fb-0cd9b94bf9cc.dkfz-snvCalling_1-0-132-1-hpc.1510221004.germline.snv_mnv.vcf.gz.tbi", 
            "file_size": 1552060, 
            "object_id": "5cdaa9fd-9fb8-5ba0-9fcd-43e816fa105d"
        }, 
        {
            "file_md5sum": "89bc86d979e1ed17ab46e9b80ba44970", 
            "file_name": "94244f28-4ba2-4aa6-a0fb-0cd9b94bf9cc.dkfz-snvCalling_1-0-132-1-hpc.1510221004.somatic.snv_mnv.vcf.gz", 
            "file_size": 757679, 
            "object_id": "b54d7c5b-3a63-52ef-aec1-2f5a360bd8c3"
        }, 
        {
            "file_md5sum": "3cb31cbb9710c5d6473ad74ea9096d2a", 
            "file_name": "94244f28-4ba2-4aa6-a0fb-0cd9b94bf9cc.dkfz-snvCalling_1-0-132-1-hpc.1510221004.somatic.snv_mnv.vcf.gz.tbi", 
            "file_size": 309442, 
            "object_id": "e3b0c456-92dd-5c7b-b1bc-54a0971d6289"
        }, 
        {
            "file_md5sum": "581bbca26eb5056d5edaedd998694357", 
            "file_name": "94244f28-4ba2-4aa6-a0fb-0cd9b94bf9cc.embl-delly_1-0-0-preFilter-hpc.150702.germline.sv.vcf.gz", 
            "file_size": 268688, 
            "object_id": "254e2b56-dee3-51ee-98fc-fd6ac9b4f158"
        }, 
        {
            "file_md5sum": "a33b5ecf26bbe3bb9d7551dff2c2cd7d", 
            "file_name": "94244f28-4ba2-4aa6-a0fb-0cd9b94bf9cc.embl-delly_1-0-0-preFilter-hpc.150702.germline.sv.vcf.gz.tbi", 
            "file_size": 24473, 
            "object_id": "740b0c5c-e98e-5391-86b9-bf896f47cba9"
        }, 
        {
            "file_md5sum": "b6e8777d934fb08c66777650774e6270", 
            "file_name": "94244f28-4ba2-4aa6-a0fb-0cd9b94bf9cc.embl-delly_1-0-0-preFilter-hpc.150702.somatic.sv.vcf.gz", 
            "file_size": 10135, 
            "object_id": "f82e2924-73d2-507a-98c5-3527d1cf007a"
        }, 
        {
            "file_md5sum": "0f03d7d5125ac36b3a7a8a8d8accfbf3", 
            "file_name": "94244f28-4ba2-4aa6-a0fb-0cd9b94bf9cc.embl-delly_1-0-0-preFilter-hpc.150702.somatic.sv.vcf.gz.tbi", 
            "file_size": 5685, 
            "object_id": "423efec4-239f-50a2-9342-463c21670661"
        }, 
        {
            "file_md5sum": "7a17a757d170349d9d9deab214c4629f", 
            "file_name": "94244f28-4ba2-4aa6-a0fb-0cd9b94bf9cc.embl-delly_1-0-0-preFilter-hpc.150702.sv.vcf.gz", 
            "file_size": 27819100, 
            "object_id": "bc18317c-64bf-5b20-8c44-8fb1a2986843"
        }, 
        {
            "file_md5sum": "3a816099cba20d99629816a3e0350d52", 
            "file_name": "94244f28-4ba2-4aa6-a0fb-0cd9b94bf9cc.embl-delly_1-0-0-preFilter-hpc.150702.sv.vcf.gz.tbi", 
            "file_size": 1171488, 
            "object_id": "95a4d4e1-016d-5240-a71c-771c0b878b7c"
        }, 
        {
            "file_md5sum": "46c68d273accf6c8fa864e6a0914b6f9", 
            "file_name": "94244f28-4ba2-4aa6-a0fb-0cd9b94bf9cc.dkfz-copyNumberEstimation_1-0-189-hpc.1510221004.somatic.cnv.tar.gz", 
            "file_size": 3698119740, 
            "object_id": "0e16230d-ae81-51af-bc2e-bbdf658dd49c"
        }, 
        {
            "file_md5sum": "b6abc090aefcb35016bef095b8a8347b", 
            "file_name": "94244f28-4ba2-4aa6-a0fb-0cd9b94bf9cc.dkfz-indelCalling_1-0-132-1-hpc.1510221004.somatic.indel.tar.gz", 
            "file_size": 627912566, 
            "object_id": "fc67f3fd-73c8-5ac6-8a70-37f43690897c"
        }, 
        {
            "file_md5sum": "eb6decd8632723f4173aa42fabf5cf58", 
            "file_name": "94244f28-4ba2-4aa6-a0fb-0cd9b94bf9cc.dkfz-snvCalling_1-0-132-1-hpc.1510221004.somatic.snv_mnv.tar.gz", 
            "file_size": 1094759745, 
            "object_id": "b3edcc15-f89d-51b2-b17e-37741f9f7370"
        }, 
        {
            "file_md5sum": "831ae6be11d574d8b251a67981216695", 
            "file_name": "94244f28-4ba2-4aa6-a0fb-0cd9b94bf9cc.embl-delly_1-0-0-preFilter-hpc.150702.germline.sv.bedpe.txt.tar.gz", 
            "file_size": 126697, 
            "object_id": "95bea7a9-39da-5ab5-91b1-b4ad712b9bad"
        }, 
        {
            "file_md5sum": "b0bad70991dc46e95678e8672df87162", 
            "file_name": "94244f28-4ba2-4aa6-a0fb-0cd9b94bf9cc.embl-delly_1-0-0-preFilter-hpc.150702.germline.sv.readname.txt.tar.gz", 
            "file_size": 11484954, 
            "object_id": "7b26d2cd-c4a1-5172-95ec-e7221b000e8c"
        }, 
        {
            "file_md5sum": "a03434864eddaf3e4fbf8ce02c094971", 
            "file_name": "94244f28-4ba2-4aa6-a0fb-0cd9b94bf9cc.embl-delly_1-0-0-preFilter-hpc.150702.somatic.sv.bedpe.txt.tar.gz", 
            "file_size": 4801, 
            "object_id": "f88dd900-b139-5cb0-92c5-92ac3daea75f"
        }, 
        {
            "file_md5sum": "ff9ad93393ac64919054595bdfd2357d", 
            "file_name": "94244f28-4ba2-4aa6-a0fb-0cd9b94bf9cc.embl-delly_1-0-0-preFilter-hpc.150702.somatic.sv.readname.txt.tar.gz", 
            "file_size": 11484953, 
            "object_id": "425e4b4a-d305-50fa-9b98-7f7d32de9860"
        }, 
        {
            "file_md5sum": "b4ab40ad94b5d9db70f4458788e6554d", 
            "file_name": "94244f28-4ba2-4aa6-a0fb-0cd9b94bf9cc.embl-delly_1-0-0-preFilter-hpc.150702.sv.log.tar.gz", 
            "file_size": 58360, 
            "object_id": "c2c4ce44-774c-53cd-84f0-e98d640ee096"
        }, 
        {
            "file_md5sum": "333514398b581ba263abecd7321eaab7", 
            "file_name": "19a38b6b-24b2-4148-83f7-c177e59937fc.xml", 
            "file_size": 51365, 
            "object_id": "83d46c8f-d0b6-5e82-9aae-ebfb35e0c540"
        }
    ], 
    "gnos_id": "19a38b6b-24b2-4148-83f7-c177e59937fc", 
    "gnos_repo": [
        "https://gtrepo-dkfz.annailabs.com/"
    ], 
    "is_santa_cruz": false, 
    "project_code": "PAEN-AU", 
    "specimen_type": null, 
    "submitter_donor_id": "ITNET-0681", 
    "submitter_sample_id": null, 
    "submitter_specimen_id": null
}