{
    "_runs_": {
        "run_1473960950_af84632f-ec1b-4060-a339-9d52279734cb": {
            "downloading": {
                "gnos-download_time": 43, 
                "start": 1473979248, 
                "stop": 1473979291, 
                "time": 43
            }
        }
    }, 
    "aliquot_id": "c9ad6b1c-baa0-45a7-b7c4-733728505b8a", 
    "available_repos": [
        {
            "https://gtrepo-osdc-icgc.annailabs.com/": {
                "file_md5sum": "00e8ae89129c05014641c643235300e7", 
                "file_size": 32748
            }
        }
    ], 
    "data_type": "Consensus-somatic-INDEL", 
    "files": [
        {
            "file_md5sum": "857b581a8e82e6efe2de49bd54e2c411", 
            "file_name": "c9ad6b1c-baa0-45a7-b7c4-733728505b8a.consensus.20160830.somatic.indel.vcf.gz", 
            "file_size": 62101, 
            "object_id": "d350ed0e-a820-59da-970d-5b1ae840ead9"
        }, 
        {
            "file_md5sum": "5d43fa26d032f7267057fe260c96a300", 
            "file_name": "c9ad6b1c-baa0-45a7-b7c4-733728505b8a.consensus.20160830.somatic.indel.vcf.gz.tbi", 
            "file_size": 30224, 
            "object_id": "f267cb4e-24e9-5149-bfdd-a7075aa6ddfa"
        }, 
        {
            "file_md5sum": "00e8ae89129c05014641c643235300e7", 
            "file_name": "c5309d16-55c7-4d4a-bcb0-b0ed32971e66.xml", 
            "file_size": 32748, 
            "object_id": "21085e33-de47-54f8-81cf-25efb9d28686"
        }
    ], 
    "gnos_id": "c5309d16-55c7-4d4a-bcb0-b0ed32971e66", 
    "gnos_repo": [
        "https://gtrepo-osdc-icgc.annailabs.com/"
    ], 
    "project_code": "RECA-EU", 
    "specimen_type": null, 
    "submitter_donor_id": "C0052", 
    "submitter_sample_id": null, 
    "submitter_specimen_id": "c9ad6b1c-baa0-45a7-b7c4-733728505b8a", 
    "vcf_workflow_result_version": "v1"
}