{
    "_runs_": {
        "run_1454298654_386647a0-5f8b-4196-bab3-c5e5a51b5314": {
            "downloading": {
                "gnos-download_time": 27, 
                "start": 1454312366, 
                "stop": 1454312394, 
                "time": 28
            }, 
            "uploading": {
                "copy_meta_time": 2, 
                "start": 1454312399, 
                "stop": 1454312415, 
                "time": 16, 
                "upload_time": 14
            }
        }
    }, 
    "aliquot_id": null, 
    "available_repos": [
        {
            "https://gtrepo-osdc-icgc.annailabs.com/": {
                "file_md5sum": "03c8439302dcf96eca182e627d528dc7", 
                "file_size": 34070
            }
        }
    ], 
    "data_type": "Muse-VCF", 
    "files": [
        {
            "file_md5sum": "4e2fb4b7392ce98039bbdb2ae9607407", 
            "file_name": "f755e9b4-c622-11e3-bf01-24c6515278c0.MUSE_1-0rc-vcf.20151217.somatic.snv_mnv.vcf.gz", 
            "file_size": 338054, 
            "object_id": "c3927d20-6acd-5087-9175-b53ccc539878"
        }, 
        {
            "file_md5sum": "9a1907d3a2c31a79c3ffd295ccaf0e65", 
            "file_name": "f755e9b4-c622-11e3-bf01-24c6515278c0.MUSE_1-0rc-vcf.20151217.somatic.snv_mnv.vcf.gz.idx", 
            "file_size": 174548, 
            "object_id": "8dda98b2-34c4-5670-a397-d51d0bc0693d"
        }, 
        {
            "file_md5sum": "03c8439302dcf96eca182e627d528dc7", 
            "file_name": "79a3d471-9c03-4f34-90e9-1e5121a30cca.xml", 
            "file_size": 34070, 
            "object_id": "07bcada6-22e0-5407-903e-da4125efd0b9"
        }
    ], 
    "gnos_id": "79a3d471-9c03-4f34-90e9-1e5121a30cca", 
    "gnos_repo": [
        "https://gtrepo-osdc-icgc.annailabs.com/"
    ], 
    "project_code": "LIRI-JP", 
    "specimen_type": null, 
    "submitter_donor_id": "RK165", 
    "submitter_sample_id": null, 
    "submitter_specimen_id": null, 
    "vcf_workflow_result_version": "v1"
}